{"name":"searching_by_keyword_football_should_display_the_corresponding_article","id":"ssvv.features.search.SearchByKeywordStory:searching_by_keyword_football_should_display_the_corresponding_article","testCaseName":"ssvv.features.search.SearchByKeywordStory","testSteps":[{"number":1,"description":"Is the home page","duration":4722,"startTime":"2022-05-04T09:17:53.894+03:00[Europe/Bucharest]","screenshots":[{"screenshot":"03b3609e4156920cf5767970950bfcc4d03b539d402662865053f4518d912ae7.png","timeStamp":1651645078615}],"result":"SUCCESS","precondition":false,"level":0},{"number":2,"description":"Looks for: football","duration":2134,"startTime":"2022-05-04T09:17:58.619+03:00[Europe/Bucharest]","screenshots":[{"screenshot":"b2522c28cd6f812a52a4750b3bf864b4e46b93b37595b15feda75634d7e667b2.png","timeStamp":1651645080753}],"result":"SUCCESS","precondition":false,"level":0,"children":[{"number":3,"description":"Enters: football","duration":359,"startTime":"2022-05-04T09:17:58.622+03:00[Europe/Bucharest]","screenshots":[{"screenshot":"868bd96f1b24b795f3f82f527e62b1930a90a0b779798a99e8252c9e916120ac.png","timeStamp":1651645078980}],"result":"SUCCESS","precondition":false,"level":1},{"number":4,"description":"Starts search","duration":1771,"startTime":"2022-05-04T09:17:58.981+03:00[Europe/Bucharest]","screenshots":[{"screenshot":"868bd96f1b24b795f3f82f527e62b1930a90a0b779798a99e8252c9e916120ac.png","timeStamp":1651645078983},{"screenshot":"b2522c28cd6f812a52a4750b3bf864b4e46b93b37595b15feda75634d7e667b2.png","timeStamp":1651645080752}],"result":"SUCCESS","precondition":false,"level":1}]},{"number":5,"description":"Should see definition: A sport played on foot in which teams attempt to get a ball into a goal or zone defended by the other team","duration":285,"startTime":"2022-05-04T09:18:00.754+03:00[Europe/Bucharest]","screenshots":[{"screenshot":"4b09eda5d8fb1998943ac476c6e7f4f5009d066f50b275622db56347a5b26aae.png","timeStamp":1651645081039}],"result":"SUCCESS","precondition":false,"level":0}],"userStory":{"id":"ssvv.features.search.SearchByKeywordStory","storyName":"Search by keyword story","storyClassName":"ssvv.features.search.SearchByKeywordStory","path":"search","type":"story"},"featureTag":{"name":"Search/Search by keyword story","type":"story","displayName":"Search/Search by keyword story"},"title":"Searching by keyword football should display the corresponding article","tags":[{"name":"Search","type":"feature","displayName":"Search"},{"name":"Search/Search by keyword story","type":"story","displayName":"Search by keyword story"},{"name":"Search","type":"capability","displayName":"Search for definitions"}],"startTime":"2022-05-04T09:17:53.662+03:00[Europe/Bucharest]","duration":7380,"projectKey":"","sessionId":"58982aaa617faa4b3e3103776feeab84","driver":"chrome","isManualTestingUpToDate":false,"manual":false,"testSource":"JUnit","order":0,"result":"SUCCESS"}